aardvark_py/LICENSE.txt
aardvark_py/README.txt
aardvark_py/__init__.py
aardvark_py/aardvark.dll
aardvark_py/aardvark_py.py
aardvark_py-5.40.dist-info/METADATA
aardvark_py-5.40.dist-info/WHEEL
aardvark_py-5.40.dist-info/top_level.txt
aardvark_py-5.40.dist-info/RECORD
