Metadata-Version: 2.1
Name: aardvark-py
Version: 5.40
Summary: Total Phase API Library
Home-page: https://www.totalphase.com/
Author: Total Phase, Inc.
Author-email: support@totalphase.com
License: Total Phase License
Platform: win32
